extractor/__init__.py
fixtractor-0.1.2.data/scripts/fixtractor
fixtractor-0.1.2.dist-info/METADATA
fixtractor-0.1.2.dist-info/WHEEL
fixtractor-0.1.2.dist-info/top_level.txt
fixtractor-0.1.2.dist-info/RECORD
